sequence_models/__init__.py
sequence_models/aaindex.py
sequence_models/collaters.py
sequence_models/constants.py
sequence_models/convolutional.py
sequence_models/datasets.py
sequence_models/esm.py
sequence_models/flip_utils.py
sequence_models/gnn.py
sequence_models/gvp.py
sequence_models/layers.py
sequence_models/losses.py
sequence_models/metrics.py
sequence_models/mixup.py
sequence_models/pdb_utils.py
sequence_models/pretrained.py
sequence_models/samplers.py
sequence_models/structure.py
sequence_models/trRosetta.py
sequence_models/trRosetta_utils.py
sequence_models/utils.py
sequence_models/vae.py
sequence_models-1.8.0.dist-info/LICENSE
sequence_models-1.8.0.dist-info/METADATA
sequence_models-1.8.0.dist-info/WHEEL
sequence_models-1.8.0.dist-info/top_level.txt
sequence_models-1.8.0.dist-info/RECORD
