Metadata-Version: 2.1
Name: sequence-models
Version: 1.8.0
Summary: Machine learning for sequences.
Home-page: https://github.com/microsoft/protein-sequence-models
Author: Kevin Yang
Author-email: yang.kevin@microsoft.com
Classifier: Programming Language :: Python :: 3
Classifier: Operating System :: OS Independent
Requires-Python: >=3.6
License-File: LICENSE
